zict/__init__.py
zict/buffer.py
zict/cache.py
zict/common.py
zict/file.py
zict/func.py
zict/lmdb.py
zict/lru.py
zict/py.typed
zict/sieve.py
zict/zip.py
zict/tests/__init__.py
zict/tests/test_buffer.py
zict/tests/test_cache.py
zict/tests/test_file.py
zict/tests/test_func.py
zict/tests/test_lmdb.py
zict/tests/test_lru.py
zict/tests/test_sieve.py
zict/tests/test_zip.py
zict/tests/utils_test.py
zict-2.2.0.dist-info/LICENSE.txt
zict-2.2.0.dist-info/METADATA
zict-2.2.0.dist-info/WHEEL
zict-2.2.0.dist-info/top_level.txt
zict-2.2.0.dist-info/RECORD
