Metadata-Version: 2.1
Name: zict
Version: 2.2.0
Summary: Mutable mapping tools
Home-page: http://zict.readthedocs.io/en/latest/
Maintainer: Matthew Rocklin
Maintainer-email: mrocklin@coiled.io
License: BSD
Keywords: mutable mapping,dict,dask
Platform: UNKNOWN
Classifier: Development Status :: 5 - Production/Stable
Classifier: License :: OSI Approved :: BSD License
Classifier: Operating System :: OS Independent
Classifier: Programming Language :: Python
Classifier: Programming Language :: Python :: 3
Classifier: Programming Language :: Python :: 3.7
Classifier: Programming Language :: Python :: 3.8
Classifier: Programming Language :: Python :: 3.9
Classifier: Programming Language :: Python :: 3.10
Requires-Python: >=3.7
License-File: LICENSE.txt
